{
  "version": 1,
  "dependencies": [
    {
      "source": {
        "git": {
          "remote": "https://github.com/jsonnet-libs/fluxcd-libsonnet.git",
          "subdir": "2.3.0"
        }
      },
      "version": "main"
    },
    {
      "source": {
        "git": {
          "remote": "https://github.com/jsonnet-libs/k8s-libsonnet.git",
          "subdir": "1.30"
        }
      },
      "version": "main"
    },
    {
      "source": {
        "git": {
          "remote": "https://github.com/jsonnet-libs/xtd.git",
          "subdir": ""
        }
      },
      "version": "master"
    },
    {
      "source": {
        "git": {
          "remote": "https://github.com/prometheus-operator/kube-prometheus.git",
          "subdir": "jsonnet/kube-prometheus"
        }
      },
      "version": "v0.13.0"
    }
  ],
  "legacyImports": false
}
